README.rst
setup.py
saolei/__init__.py
saolei.egg-info/PKG-INFO
saolei.egg-info/SOURCES.txt
saolei.egg-info/dependency_links.txt
saolei.egg-info/top_level.txt