Metadata-Version: 2.1
Name: saolei
Version: 1.0.0
Summary: A minesweeper game.
Home-page: https://www.github.com/
Author: bob
Author-email: 56141537@qq.com
License: UNKNOWN
Platform: UNKNOWN
Classifier: Programming Language :: Python :: 3
Classifier: License :: OSI Approved :: MIT License
Classifier: Operating System :: OS Independent
